govee_local_api/__init__.py
govee_local_api/controller.py
govee_local_api/device.py
govee_local_api/device_registry.py
govee_local_api/light_capabilities.py
govee_local_api/message.py
govee_local_api-2.3.0.dist-info/METADATA
govee_local_api-2.3.0.dist-info/WHEEL
govee_local_api-2.3.0.dist-info/licenses/LICENSE
govee_local_api-2.3.0.dist-info/RECORD
